{
	"entries":[
		{
			"type":"category",
			"category":"",
			"name":"gac14:items/keys",
			"display":{
				"text":"Crate Keys",
				"color":"gold",
				"bold":true
			},
			"icon":{
				"in-game":"minecraft:tripwire_hook",
				"site":"images/icons/keys.jpg"
			}
		},
		{
			"type":"item",
			"category":"gac14:items/keys",
			"name":"gac14:keys/common",
			"display":{
				"text":"Common Crate Key",
				"color":"gold",
				"bold":true
			},
			"icon":{
				"in-game":"minecraft:tripwire_hook",
				"site":"images/icons/keys.jpg"
			},
			"result":"gac14:loot/categories/keys/common/c1",
			"value":{
				"ammount":1.0,
				"currency":"CAD"
			},
			"code":"c9bdabe8-30be-11e9-b499-d663bd873d93"
		},
		{
			"type":"item",
			"category":"gac14:items/keys",
			"name":"gac14:keys/uncommon",
			"display":{
				"text":"Uncommon Crate Key",
				"color":"gold",
				"bold":true
			},
			"icon":{
				"in-game":"minecraft:gold_nugget",
				"site":"images/icons/uncommon_key.jpg"
			},
			"result":"gac14:loot/categories/keys/uncommon/u1",
			"value":{
				"ammount":1.75,
				"currency":"CAD"
			},
			"code":"b4993dba-3125-11e9-8fb3-d663bd873d93"
		},
		{
			"type":"item",
			"category":"gac14:items/keys",
			"name":"gac14:keys/rare",
			"display":{
				"text":"Rare Crate Key",
				"color":"gold",
				"bold":true
			},
			"icon":{
				"in-game":"minecraft:golden_carrot",
				"site":"images/icons/rare_key.jpg"
			},
			"result":"gac14:loot/categories/keys/rare/r1",
			"value":{
				"ammount":2.25,
				"currency":"CAD"
			},
			"code":"a1ebf346-312b-11e9-b210-d663bd873d93"
		},
		{
			"type":"item",
			"category":"gac14:items/keys",
			"name":"gac14:keys/legendary",
			"display":{
				"text":"Legendary Crate Key",
				"color":"purple",
				"bold":true
			},
			"icon":{
				"in-game":"minecraft:eye_of_ender",
				"site":"images/icons/legendary_key.jpg"
			},
			"result":"gac14:loot/categories/keys/legendary/l1",
			"value":{
				"ammount":3,
				"currency":"CAD"
			},
			"code":"286b1848-312c-11e9-b210-d663bd873d93"
		},
		{
			"type":"item",
			"category":"gac14:items/keys",
			"name":"gac14:keys/mythical",
			"display":{
				"text":"Mythical Crate Key",
				"color":"purple",
				"bold":true
			},
			"icon":{
				"in-game":"minecraft:nether_start",
				"site":"images/icons/mythic_key.jpg"
			},
			"result":"gac14:loot/categories/keys/mythic/m1",
			"value":{
				"ammount":5,
				"currency":"CAD"
			},
			"code":"7f234e8a-312c-11e9-b210-d663bd873d93"
		}
	]
}